{
  "timestamp": "2026-03-15T21:40:10.436081",
  "problema": {
    "M": 2,
    "N": 3,
    "P_idle": [
      100,
      120
    ],
    "P_dynamic": [
      50,
      60
    ],
    "C_capacity": [
      4,
      5
    ],
    "u_cpu": [
      2,
      1,
      3
    ]
  },
  "qubo_info": {
    "n_variabili_originali": 8,
    "n_continuous": 2,
    "n_original_total": 10,
    "n_slack_variables": 6,
    "n_variabili_totali_qubo": 14,
    "n_termini_quadratici": 59,
    "n_termini_lineari": 8,
    "matrice_Q": [
      [
        14196.0,
        0.0,
        -14096.0,
        0.0,
        -7048.0,
        0.0,
        -21144.0,
        0.0,
        -7048.0,
        -14096.0,
        -7048.0,
        0.0,
        0.0,
        0.0
      ],
      [
        0.0,
        22145.0,
        0.0,
        -17620.0,
        0.0,
        -8810.0,
        0.0,
        -26430.0,
        0.0,
        0.0,
        0.0,
        -8810.0,
        -17620.0,
        -17620.0
      ],
      [
        -14096.0,
        0.0,
        2743.0,
        1762.0,
        3524.0,
        0.0,
        10572.0,
        0.0,
        3524.0,
        7048.0,
        3524.0,
        0.0,
        0.0,
        0.0
      ],
      [
        0.0,
        -17620.0,
        1762.0,
        2763.0,
        0.0,
        3524.0,
        0.0,
        10572.0,
        0.0,
        0.0,
        0.0,
        3524.0,
        7048.0,
        7048.0
      ],
      [
        -7048.0,
        0.0,
        3524.0,
        0.0,
        50.0,
        1762.0,
        5286.0,
        0.0,
        1762.0,
        3524.0,
        1762.0,
        0.0,
        0.0,
        0.0
      ],
      [
        0.0,
        -8810.0,
        0.0,
        3524.0,
        1762.0,
        60.0,
        0.0,
        5286.0,
        0.0,
        0.0,
        0.0,
        1762.0,
        3524.0,
        3524.0
      ],
      [
        -21144.0,
        0.0,
        10572.0,
        0.0,
        5286.0,
        0.0,
        7198.0,
        1762.0,
        5286.0,
        10572.0,
        5286.0,
        0.0,
        0.0,
        0.0
      ],
      [
        0.0,
        -26430.0,
        0.0,
        10572.0,
        0.0,
        5286.0,
        1762.0,
        7228.0,
        0.0,
        0.0,
        0.0,
        5286.0,
        10572.0,
        10572.0
      ],
      [
        -7048.0,
        0.0,
        3524.0,
        0.0,
        1762.0,
        0.0,
        5286.0,
        0.0,
        881.0,
        3524.0,
        1762.0,
        0.0,
        0.0,
        0.0
      ],
      [
        -14096.0,
        0.0,
        7048.0,
        0.0,
        3524.0,
        0.0,
        10572.0,
        0.0,
        3524.0,
        3524.0,
        3524.0,
        0.0,
        0.0,
        0.0
      ],
      [
        -7048.0,
        0.0,
        3524.0,
        0.0,
        1762.0,
        0.0,
        5286.0,
        0.0,
        1762.0,
        3524.0,
        881.0,
        0.0,
        0.0,
        0.0
      ],
      [
        0.0,
        -8810.0,
        0.0,
        3524.0,
        0.0,
        1762.0,
        0.0,
        5286.0,
        0.0,
        0.0,
        0.0,
        881.0,
        3524.0,
        3524.0
      ],
      [
        0.0,
        -17620.0,
        0.0,
        7048.0,
        0.0,
        3524.0,
        0.0,
        10572.0,
        0.0,
        0.0,
        0.0,
        3524.0,
        3524.0,
        7048.0
      ],
      [
        0.0,
        -17620.0,
        0.0,
        7048.0,
        0.0,
        3524.0,
        0.0,
        10572.0,
        0.0,
        0.0,
        0.0,
        3524.0,
        7048.0,
        3524.0
      ]
    ]
  },
  "continuous_subproblem": {
    "n_variabili_continue": 2,
    "n_vincoli": 7,
    "n_eq": 5,
    "n_ineq": 2
  },
  "admm_classico": {
    "valore_obiettivo": 538.4716162319501,
    "iterazioni": 68,
    "converged": false,
    "residui_primali": [
      1.7303187567613085,
      1.7301464169263248,
      1.7282276585855796,
      1.7278488124219795,
      1.7257148077251894,
      1.725089691696448,
      1.722682156209003,
      1.5073968391694403,
      1.4240626748565717,
      1.4229399727933119,
      1.4203309598987583,
      1.418848805221691,
      1.2288889131769631,
      1.1766649481489022,
      1.1733487770962139,
      1.0971989966978724,
      0.8999420275094289,
      1.0553956483002198,
      0.840085601424454,
      1.0090728668710727,
      0.9356636315079676,
      0.3826305031791945,
      0.353428380769498,
      0.6103072388587825,
      0.38938079599090963,
      0.35227082182361114,
      0.6104380757398022,
      0.38787600420971313,
      0.5992736866866203,
      0.39018974988491767,
      0.35252641080375535,
      0.6071993771621013,
      0.3876261398831518,
      0.345882301169186,
      0.607418025382834,
      0.3846123976608031,
      0.5364871465249732,
      0.38781105746632377,
      0.3410771091169522,
      0.6019725269981213,
      0.3830593164154934,
      0.351504158449684,
      0.36410032669242187,
      0.3259965366205605,
      0.03175029035677765,
      0.02519985995182585,
      0.023312603948994863,
      0.021423296594900585,
      0.019528638309018822,
      0.013979368806215194,
      0.008430395645121817,
      0.007424553301510406,
      0.006500680292472753,
      0.005623163305661871,
      0.0047983414853167245,
      0.004034793418448448,
      0.003340147591687372,
      0.0027183114371244245,
      0.0021718079129477404,
      0.001731301614788691,
      0.0013231516318662425,
      0.0009779481654747812,
      0.0007139220679775228,
      0.0005079872539037844,
      0.00035135200099470896,
      0.0002557306863390994,
      0.00016370162678175756,
      9.796905545591338e-05
    ],
    "s_servers": [
      1,
      1
    ],
    "v_allocation": [
      [
        0,
        1
      ],
      [
        1,
        0
      ],
      [
        1,
        0
      ]
    ],
    "l_continuous": [
      3.9694323246624266,
      1.9999999999804792
    ],
    "cpu_usage_per_server": [
      4.0,
      2.0
    ],
    "energia_idle": 220.0,
    "energia_dynamic": 320.0,
    "energia_totale": 540.0
  },
  "admm_qaoa": {
    "valore_obiettivo": 549.999999975737,
    "iterazioni": 100,
    "converged": false,
    "residui_primali": [
      1.7303187567613085,
      1.7301464169263248,
      1.7282276585855794,
      1.7278488124219795,
      1.7257148077251894,
      1.725089691696448,
      1.6053334562953552,
      1.4253068907148105,
      1.4245945989442776,
      1.640259608013079,
      1.4212015354702217,
      1.4189298853862702,
      1.1939910305766135,
      1.1230831388107576,
      1.1223010962175417,
      1.1176324614972177,
      0.9593775270406051,
      0.9240561237580646,
      0.9189463249064599,
      0.9877073557358421,
      0.8073005035377327,
      0.4724218246822621,
      1.0676389759268425,
      0.6084702082004199,
      0.4690024835591138,
      0.5631917978038363,
      0.8147279551981974,
      0.5804972773069271,
      0.48396551081441286,
      0.5644153350470369,
      0.7952145133624478,
      0.575337841186597,
      1.034375497517495,
      0.575371943276015,
      0.45740987210143513,
      0.8668269090219304,
      0.04382481421880476,
      0.04198633777376592,
      0.7464369139881106,
      0.552292241690046,
      0.5275179190672641,
      0.0628862309544154,
      0.03160350942759131,
      0.029743832285112123,
      0.027895239197518445,
      0.026000067588427763,
      0.02407013441765237,
      0.021643526670409825,
      0.019704678069712593,
      0.5349857847181024,
      0.26867891360618,
      0.10749875377680805,
      0.036568284481538885,
      0.030379708934890157,
      0.46344242009984166,
      0.32596818303551983,
      0.43811366737972623,
      0.3582002684787859,
      0.4159333829327972,
      0.3461310007282186,
      0.09176747259560848,
      0.581437814488457,
      0.15075767307693166,
      0.10726068489812304,
      0.5770560625597881,
      0.37630661412171174,
      0.28454132371289825,
      0.3309450776601874,
      0.29064304974367733,
      0.2197169597810271,
      0.12276438465542955,
      0.11224314340390082,
      0.04869226972635735,
      0.021905941175641833,
      0.010125750094752665,
      0.004473205690359152,
      0.3498362516561023,
      0.16872545137319445,
      0.0673472840930063,
      0.02760289276812606,
      0.07985619807236743,
      0.025140065246558478,
      0.007948263243112525,
      0.0029607951885185792,
      0.1933780344204687,
      0.04487717200598942,
      0.009718164794282405,
      0.001975441826064437,
      0.09073739575968709,
      0.1397253231355004,
      0.025726382199648103,
      0.009462936238669907,
      0.08809845114247934,
      0.03384810420847735,
      0.006412534041360837,
      0.003858599591596966,
      0.00286781637998614,
      0.0021611843196838055,
      0.0016419273595396611,
      0.0012566562754385145
    ],
    "s_servers": [
      1,
      1
    ],
    "v_allocation": [
      [
        1,
        0
      ],
      [
        1,
        0
      ],
      [
        0,
        1
      ]
    ],
    "l_continuous": [
      2.99999999978516,
      2.9999999997746505
    ],
    "cpu_usage_per_server": [
      3.0,
      3.0
    ],
    "energia_idle": 220.0,
    "energia_dynamic": 330.0,
    "energia_totale": 550.0
  },
  "ising": {
    "coefficienti_zz": [
      {
        "qubits": [
          0,
          2
        ],
        "value": -3524.0
      },
      {
        "qubits": [
          0,
          4
        ],
        "value": -1762.0
      },
      {
        "qubits": [
          0,
          6
        ],
        "value": -5286.0
      },
      {
        "qubits": [
          0,
          8
        ],
        "value": -1762.0
      },
      {
        "qubits": [
          0,
          9
        ],
        "value": -3524.0
      },
      {
        "qubits": [
          0,
          10
        ],
        "value": -1762.0
      },
      {
        "qubits": [
          1,
          3
        ],
        "value": -4405.0
      },
      {
        "qubits": [
          1,
          5
        ],
        "value": -2202.5
      },
      {
        "qubits": [
          1,
          7
        ],
        "value": -6607.5
      },
      {
        "qubits": [
          1,
          11
        ],
        "value": -2202.5
      },
      {
        "qubits": [
          1,
          12
        ],
        "value": -4405.0
      },
      {
        "qubits": [
          1,
          13
        ],
        "value": -4405.0
      },
      {
        "qubits": [
          2,
          3
        ],
        "value": 440.5
      },
      {
        "qubits": [
          2,
          4
        ],
        "value": 881.0
      },
      {
        "qubits": [
          2,
          6
        ],
        "value": 2643.0
      },
      {
        "qubits": [
          2,
          8
        ],
        "value": 881.0
      },
      {
        "qubits": [
          2,
          9
        ],
        "value": 1762.0
      },
      {
        "qubits": [
          2,
          10
        ],
        "value": 881.0
      },
      {
        "qubits": [
          3,
          5
        ],
        "value": 881.0
      },
      {
        "qubits": [
          3,
          7
        ],
        "value": 2643.0
      },
      {
        "qubits": [
          3,
          11
        ],
        "value": 881.0
      },
      {
        "qubits": [
          3,
          12
        ],
        "value": 1762.0
      },
      {
        "qubits": [
          3,
          13
        ],
        "value": 1762.0
      },
      {
        "qubits": [
          4,
          5
        ],
        "value": 440.5
      },
      {
        "qubits": [
          4,
          6
        ],
        "value": 1321.5
      },
      {
        "qubits": [
          4,
          8
        ],
        "value": 440.5
      },
      {
        "qubits": [
          4,
          9
        ],
        "value": 881.0
      },
      {
        "qubits": [
          4,
          10
        ],
        "value": 440.5
      },
      {
        "qubits": [
          5,
          7
        ],
        "value": 1321.5
      },
      {
        "qubits": [
          5,
          11
        ],
        "value": 440.5
      },
      {
        "qubits": [
          5,
          12
        ],
        "value": 881.0
      },
      {
        "qubits": [
          5,
          13
        ],
        "value": 881.0
      },
      {
        "qubits": [
          6,
          7
        ],
        "value": 440.5
      },
      {
        "qubits": [
          6,
          8
        ],
        "value": 1321.5
      },
      {
        "qubits": [
          6,
          9
        ],
        "value": 2643.0
      },
      {
        "qubits": [
          6,
          10
        ],
        "value": 1321.5
      },
      {
        "qubits": [
          7,
          11
        ],
        "value": 1321.5
      },
      {
        "qubits": [
          7,
          12
        ],
        "value": 2643.0
      },
      {
        "qubits": [
          7,
          13
        ],
        "value": 2643.0
      },
      {
        "qubits": [
          8,
          9
        ],
        "value": 881.0
      },
      {
        "qubits": [
          8,
          10
        ],
        "value": 440.5
      },
      {
        "qubits": [
          9,
          10
        ],
        "value": 881.0
      },
      {
        "qubits": [
          11,
          12
        ],
        "value": 881.0
      },
      {
        "qubits": [
          11,
          13
        ],
        "value": 881.0
      },
      {
        "qubits": [
          12,
          13
        ],
        "value": 1762.0
      }
    ],
    "coefficienti_z": [
      {
        "qubit": 0,
        "value": 10522.0
      },
      {
        "qubit": 2,
        "value": -5336.0
      },
      {
        "qubit": 4,
        "value": -2668.0
      },
      {
        "qubit": 6,
        "value": -8004.0
      },
      {
        "qubit": 1,
        "value": 13155.0
      },
      {
        "qubit": 3,
        "value": -5346.0
      },
      {
        "qubit": 5,
        "value": -2673.0
      },
      {
        "qubit": 7,
        "value": -8019.0
      },
      {
        "qubit": 8,
        "value": -2643.0
      },
      {
        "qubit": 9,
        "value": -5286.0
      },
      {
        "qubit": 10,
        "value": -2643.0
      },
      {
        "qubit": 11,
        "value": -2643.0
      },
      {
        "qubit": 12,
        "value": -5286.0
      },
      {
        "qubit": 13,
        "value": -5286.0
      }
    ],
    "offset": 36120.5
  },
  "qaoa_circuit": {
    "n_qubits": 14,
    "reps": 2,
    "depth": 5,
    "gamma": [
      2.3533,
      5.9735
    ],
    "beta": [
      2.2996,
      1.8807
    ]
  }
}