[
  {
    "M": 2,
    "N": 3,
    "worker_status": "error",
    "worker_error": "'P_idle'",
    "worker_traceback": "Traceback (most recent call last):\n  File \"C:\\Users\\lgandolfi\\AppData\\Local\\Temp\\ipykernel_29788\\3856639277.py\", line 10, in _worker_run\n    result = run_configuration(\n             ^^^^^^^^^^^^^^^^^^\n  File \"C:\\Users\\lgandolfi\\AppData\\Local\\Temp\\ipykernel_29788\\4002674371.py\", line 18, in run_configuration\n    qp = _build_qp(M, N, params)\n         ^^^^^^^^^^^^^^^^^^^^^^^\n  File \"C:\\Users\\lgandolfi\\AppData\\Local\\Temp\\ipykernel_29788\\4286199268.py\", line 3, in _build_qp\n    PI = params[\"P_idle\"]\n         ~~~~~~^^^^^^^^^^\nKeyError: 'P_idle'\n",
    "n_binary_vars_original": null,
    "n_slack_vars": null,
    "n_qubo_vars": null,
    "n_qubits": null,
    "qubo_sparsity": null,
    "continuous_vars": null,
    "feasible": null,
    "classical_obj": null,
    "classical_iter": null,
    "classical_converged": null,
    "classical_time_sec": null,
    "classical_residuals": null,
    "classical_energy_total": null,
    "classical_servers_on": null,
    "qaoa_obj": null,
    "qaoa_iter": null,
    "qaoa_converged": null,
    "qaoa_time_sec": null,
    "qaoa_residuals": null,
    "qaoa_energy_total": null,
    "qaoa_error": true,
    "qaoa_error_msg": "'P_idle'",
    "qaoa_skipped": null,
    "qaoa_skip_reason": "",
    "obj_diff_pct": null,
    "iter_ratio": null,
    "time_ratio": null,
    "worker_wall_time_sec": 0.0006
  },
  {
    "M": 3,
    "N": 3,
    "worker_status": "error",
    "worker_error": "'P_idle'",
    "worker_traceback": "Traceback (most recent call last):\n  File \"C:\\Users\\lgandolfi\\AppData\\Local\\Temp\\ipykernel_29788\\3856639277.py\", line 10, in _worker_run\n    result = run_configuration(\n             ^^^^^^^^^^^^^^^^^^\n  File \"C:\\Users\\lgandolfi\\AppData\\Local\\Temp\\ipykernel_29788\\4002674371.py\", line 18, in run_configuration\n    qp = _build_qp(M, N, params)\n         ^^^^^^^^^^^^^^^^^^^^^^^\n  File \"C:\\Users\\lgandolfi\\AppData\\Local\\Temp\\ipykernel_29788\\4286199268.py\", line 3, in _build_qp\n    PI = params[\"P_idle\"]\n         ~~~~~~^^^^^^^^^^\nKeyError: 'P_idle'\n",
    "n_binary_vars_original": null,
    "n_slack_vars": null,
    "n_qubo_vars": null,
    "n_qubits": null,
    "qubo_sparsity": null,
    "continuous_vars": null,
    "feasible": null,
    "classical_obj": null,
    "classical_iter": null,
    "classical_converged": null,
    "classical_time_sec": null,
    "classical_residuals": null,
    "classical_energy_total": null,
    "classical_servers_on": null,
    "qaoa_obj": null,
    "qaoa_iter": null,
    "qaoa_converged": null,
    "qaoa_time_sec": null,
    "qaoa_residuals": null,
    "qaoa_energy_total": null,
    "qaoa_error": true,
    "qaoa_error_msg": "'P_idle'",
    "qaoa_skipped": null,
    "qaoa_skip_reason": "",
    "obj_diff_pct": null,
    "iter_ratio": null,
    "time_ratio": null,
    "worker_wall_time_sec": 0.0002
  },
  {
    "M": 3,
    "N": 4,
    "worker_status": "error",
    "worker_error": "'P_idle'",
    "worker_traceback": "Traceback (most recent call last):\n  File \"C:\\Users\\lgandolfi\\AppData\\Local\\Temp\\ipykernel_29788\\3856639277.py\", line 10, in _worker_run\n    result = run_configuration(\n             ^^^^^^^^^^^^^^^^^^\n  File \"C:\\Users\\lgandolfi\\AppData\\Local\\Temp\\ipykernel_29788\\4002674371.py\", line 18, in run_configuration\n    qp = _build_qp(M, N, params)\n         ^^^^^^^^^^^^^^^^^^^^^^^\n  File \"C:\\Users\\lgandolfi\\AppData\\Local\\Temp\\ipykernel_29788\\4286199268.py\", line 3, in _build_qp\n    PI = params[\"P_idle\"]\n         ~~~~~~^^^^^^^^^^\nKeyError: 'P_idle'\n",
    "n_binary_vars_original": null,
    "n_slack_vars": null,
    "n_qubo_vars": null,
    "n_qubits": null,
    "qubo_sparsity": null,
    "continuous_vars": null,
    "feasible": null,
    "classical_obj": null,
    "classical_iter": null,
    "classical_converged": null,
    "classical_time_sec": null,
    "classical_residuals": null,
    "classical_energy_total": null,
    "classical_servers_on": null,
    "qaoa_obj": null,
    "qaoa_iter": null,
    "qaoa_converged": null,
    "qaoa_time_sec": null,
    "qaoa_residuals": null,
    "qaoa_energy_total": null,
    "qaoa_error": true,
    "qaoa_error_msg": "'P_idle'",
    "qaoa_skipped": null,
    "qaoa_skip_reason": "",
    "obj_diff_pct": null,
    "iter_ratio": null,
    "time_ratio": null,
    "worker_wall_time_sec": 0.0001
  },
  {
    "M": 4,
    "N": 4,
    "worker_status": "error",
    "worker_error": "'P_idle'",
    "worker_traceback": "Traceback (most recent call last):\n  File \"C:\\Users\\lgandolfi\\AppData\\Local\\Temp\\ipykernel_29788\\3856639277.py\", line 10, in _worker_run\n    result = run_configuration(\n             ^^^^^^^^^^^^^^^^^^\n  File \"C:\\Users\\lgandolfi\\AppData\\Local\\Temp\\ipykernel_29788\\4002674371.py\", line 18, in run_configuration\n    qp = _build_qp(M, N, params)\n         ^^^^^^^^^^^^^^^^^^^^^^^\n  File \"C:\\Users\\lgandolfi\\AppData\\Local\\Temp\\ipykernel_29788\\4286199268.py\", line 3, in _build_qp\n    PI = params[\"P_idle\"]\n         ~~~~~~^^^^^^^^^^\nKeyError: 'P_idle'\n",
    "n_binary_vars_original": null,
    "n_slack_vars": null,
    "n_qubo_vars": null,
    "n_qubits": null,
    "qubo_sparsity": null,
    "continuous_vars": null,
    "feasible": null,
    "classical_obj": null,
    "classical_iter": null,
    "classical_converged": null,
    "classical_time_sec": null,
    "classical_residuals": null,
    "classical_energy_total": null,
    "classical_servers_on": null,
    "qaoa_obj": null,
    "qaoa_iter": null,
    "qaoa_converged": null,
    "qaoa_time_sec": null,
    "qaoa_residuals": null,
    "qaoa_energy_total": null,
    "qaoa_error": true,
    "qaoa_error_msg": "'P_idle'",
    "qaoa_skipped": null,
    "qaoa_skip_reason": "",
    "obj_diff_pct": null,
    "iter_ratio": null,
    "time_ratio": null,
    "worker_wall_time_sec": 0.0001
  },
  {
    "M": 4,
    "N": 5,
    "worker_status": "error",
    "worker_error": "'P_idle'",
    "worker_traceback": "Traceback (most recent call last):\n  File \"C:\\Users\\lgandolfi\\AppData\\Local\\Temp\\ipykernel_29788\\3856639277.py\", line 10, in _worker_run\n    result = run_configuration(\n             ^^^^^^^^^^^^^^^^^^\n  File \"C:\\Users\\lgandolfi\\AppData\\Local\\Temp\\ipykernel_29788\\4002674371.py\", line 18, in run_configuration\n    qp = _build_qp(M, N, params)\n         ^^^^^^^^^^^^^^^^^^^^^^^\n  File \"C:\\Users\\lgandolfi\\AppData\\Local\\Temp\\ipykernel_29788\\4286199268.py\", line 3, in _build_qp\n    PI = params[\"P_idle\"]\n         ~~~~~~^^^^^^^^^^\nKeyError: 'P_idle'\n",
    "n_binary_vars_original": null,
    "n_slack_vars": null,
    "n_qubo_vars": null,
    "n_qubits": null,
    "qubo_sparsity": null,
    "continuous_vars": null,
    "feasible": null,
    "classical_obj": null,
    "classical_iter": null,
    "classical_converged": null,
    "classical_time_sec": null,
    "classical_residuals": null,
    "classical_energy_total": null,
    "classical_servers_on": null,
    "qaoa_obj": null,
    "qaoa_iter": null,
    "qaoa_converged": null,
    "qaoa_time_sec": null,
    "qaoa_residuals": null,
    "qaoa_energy_total": null,
    "qaoa_error": true,
    "qaoa_error_msg": "'P_idle'",
    "qaoa_skipped": null,
    "qaoa_skip_reason": "",
    "obj_diff_pct": null,
    "iter_ratio": null,
    "time_ratio": null,
    "worker_wall_time_sec": 0.0001
  },
  {
    "M": 5,
    "N": 5,
    "worker_status": "error",
    "worker_error": "'P_idle'",
    "worker_traceback": "Traceback (most recent call last):\n  File \"C:\\Users\\lgandolfi\\AppData\\Local\\Temp\\ipykernel_29788\\3856639277.py\", line 10, in _worker_run\n    result = run_configuration(\n             ^^^^^^^^^^^^^^^^^^\n  File \"C:\\Users\\lgandolfi\\AppData\\Local\\Temp\\ipykernel_29788\\4002674371.py\", line 18, in run_configuration\n    qp = _build_qp(M, N, params)\n         ^^^^^^^^^^^^^^^^^^^^^^^\n  File \"C:\\Users\\lgandolfi\\AppData\\Local\\Temp\\ipykernel_29788\\4286199268.py\", line 3, in _build_qp\n    PI = params[\"P_idle\"]\n         ~~~~~~^^^^^^^^^^\nKeyError: 'P_idle'\n",
    "n_binary_vars_original": null,
    "n_slack_vars": null,
    "n_qubo_vars": null,
    "n_qubits": null,
    "qubo_sparsity": null,
    "continuous_vars": null,
    "feasible": null,
    "classical_obj": null,
    "classical_iter": null,
    "classical_converged": null,
    "classical_time_sec": null,
    "classical_residuals": null,
    "classical_energy_total": null,
    "classical_servers_on": null,
    "qaoa_obj": null,
    "qaoa_iter": null,
    "qaoa_converged": null,
    "qaoa_time_sec": null,
    "qaoa_residuals": null,
    "qaoa_energy_total": null,
    "qaoa_error": true,
    "qaoa_error_msg": "'P_idle'",
    "qaoa_skipped": null,
    "qaoa_skip_reason": "",
    "obj_diff_pct": null,
    "iter_ratio": null,
    "time_ratio": null,
    "worker_wall_time_sec": 0.0001
  }
]